rich/__init__.py
rich/__main__.py
rich/_cell_widths.py
rich/_emoji_codes.py
rich/_emoji_replace.py
rich/_export_format.py
rich/_extension.py
rich/_inspect.py
rich/_log_render.py
rich/_loop.py
rich/_palettes.py
rich/_pick.py
rich/_ratio.py
rich/_spinners.py
rich/_stack.py
rich/_timer.py
rich/_win32_console.py
rich/_windows.py
rich/_windows_renderer.py
rich/_wrap.py
rich/abc.py
rich/align.py
rich/ansi.py
rich/bar.py
rich/box.py
rich/cells.py
rich/color.py
rich/color_triplet.py
rich/columns.py
rich/console.py
rich/constrain.py
rich/containers.py
rich/control.py
rich/default_styles.py
rich/diagnose.py
rich/emoji.py
rich/errors.py
rich/file_proxy.py
rich/filesize.py
rich/highlighter.py
rich/json.py
rich/jupyter.py
rich/layout.py
rich/live.py
rich/live_render.py
rich/logging.py
rich/markdown.py
rich/markup.py
rich/measure.py
rich/padding.py
rich/pager.py
rich/palette.py
rich/panel.py
rich/pretty.py
rich/progress.py
rich/progress_bar.py
rich/prompt.py
rich/protocol.py
rich/py.typed
rich/region.py
rich/repr.py
rich/rule.py
rich/scope.py
rich/screen.py
rich/segment.py
rich/spinner.py
rich/status.py
rich/style.py
rich/styled.py
rich/syntax.py
rich/table.py
rich/terminal_theme.py
rich/text.py
rich/theme.py
rich/themes.py
rich/traceback.py
rich/tree.py
rich-12.5.0.dist-info/LICENSE
rich-12.5.0.dist-info/WHEEL
rich-12.5.0.dist-info/METADATA
rich-12.5.0.dist-info/RECORD
