Metadata-Version: 2.1
Name: rich
Version: 12.5.0
Summary: Render rich text, tables, progress bars, syntax highlighting, markdown and more to the terminal
Home-page: https://github.com/willmcgugan/rich
License: MIT
Author: Will McGugan
Author-email: willmcgugan@gmail.com
Requires-Python: >=3.6.3,<4.0.0
Classifier: Development Status :: 5 - Production/Stable
Classifier: Environment :: Console
Classifier: Framework :: IPython
Classifier: Intended Audience :: Developers
Classifier: License :: OSI Approved :: MIT License
Classifier: Operating System :: MacOS
Classifier: Operating System :: Microsoft :: Windows
Classifier: Operating System :: POSIX :: Linux
Classifier: Programming Language :: Python :: 3
Classifier: Programming Language :: Python :: 3.10
Classifier: Programming Language :: Python :: 3.6
Classifier: Programming Language :: Python :: 3.7
Classifier: Programming Language :: Python :: 3.8
Classifier: Programming Language :: Python :: 3.9
Classifier: Typing :: Typed
Provides-Extra: jupyter
Requires-Dist: commonmark (>=0.9.0,<0.10.0)
Requires-Dist: dataclasses (>=0.7,<0.9); python_version < "3.7"
Requires-Dist: ipywidgets (>=7.5.1,<8.0.0); extra == "jupyter"
Requires-Dist: pygments (>=2.6.0,<3.0.0)
Requires-Dist: typing-extensions (>=4.0.0,<5.0); python_version < "3.9"
Project-URL: Documentation, https://rich.readthedocs.io/en/latest/
